{
  "uuid": "67cf3796-296c-4812-9fa1-e74eb7a0b954",
  "shortName": "Robot Example",
  "longName": "Robot Example",
  "companyName": "Chris Lewis",
  "versionCode": 1,
  "versionLabel": "1.0",
  "watchapp": {
    "watchface": false
  },
  "appKeys": {
    "dummy": 0
  },
  "resources": {
    "media": [
      {
        "type":"png",
        "name":"ROBOT_UP",
        "file":"images/robot_up.png"
      },
      {
        "type":"png",
        "name":"ROBOT_DOWN",
        "file":"images/robot_down.png"
      },
      {
        "type":"png",
        "name":"ROBOT_RIGHT",
        "file":"images/robot_right.png"
      },
      {
        "type":"png",
        "name":"ROBOT_LEFT",
        "file":"images/robot_left.png"
      }
    ]
  }
}
